cleverbotfreeapi/__init__.py
cleverbotfreeapi/cleverbotfreeapi.py
cleverbotfreeapi-1.1.1.dist-info/LICENSE.txt
cleverbotfreeapi-1.1.1.dist-info/METADATA
cleverbotfreeapi-1.1.1.dist-info/WHEEL
cleverbotfreeapi-1.1.1.dist-info/top_level.txt
cleverbotfreeapi-1.1.1.dist-info/RECORD
