Metadata-Version: 2.1
Name: cleverbotfreeapi
Version: 1.1.1
Summary: Simple unofficial package to interact with the same API that the Cleverbot website uses for free.
Home-page: https://github.com/Deftera186/cleverbotfreeapi
Author: Liav Mordouch
Author-email: liavmordouch@gmail.com
License: UNKNOWN
Platform: UNKNOWN
Classifier: Programming Language :: Python :: 3
Classifier: License :: OSI Approved :: MIT License
License-File: LICENSE.txt
Requires-Dist: requests
